src/riscv_top.v
module riscv_top (
    input wire clk,
    input wire rst,
    output wire [31:0] writedata,
    output wire [31:0] dataadr,
    output wire memwrite
  );

  wire [31:0] pc, instr, readdata;

  // Instantiate Processor (Controller + Datapath)
  // For simplicity in this single-cycle design, we can keep everything in riscv_top or separate.
  // I will instantiate the memories here and the rest in a "riscv" module or just put everything here.
  // Given the lab manual structure, I'll put the datapath and controller here.

  wire [31:0] pcnext, pcplus4, pctarget;
  wire [31:0] immext;
  wire [31:0] srca, srcb;
  wire [31:0] aluout; // dataadr
  wire [31:0] result;
  wire zero, pcsrc, alusrc, regwrite, jump;
  wire [1:0] resultsrc;
  wire [2:0] immsrc;
  wire [3:0] alucontrol;

  // Controller
  controller c (
               .op(instr[6:0]),
               .funct3(instr[14:12]),
               .funct7b5(instr[30]),
               .zero(zero),
               .resultsrc(resultsrc),
               .memwrite(memwrite),
               .pcsrc(pcsrc),
               .alusrc(alusrc),
               .regwrite(regwrite),
               .immsrc(immsrc),
               .alucontrol(alucontrol)
             );

  // Datapath

  // PC Logic
  mux2 #(32) pcmux (
         .d0(pcplus4),
         .d1(pctarget),
         .s(pcsrc),
         .y(pcnext)
       );

  pc pcreg (
       .clk(clk),
       .rst(rst),
       .pc_next(pcnext),
       .pc(pc)
     );

  adder pcadd4 (
          .a(pc),
          .b(32'd4),
          .y(pcplus4)
        );

  adder pcaddbranch (
          .a(pc),
          .b(immext),
          .y(pctarget)
        );

  // Instruction Memory
  inst_mem imem (
             .a(pc),
             .rd(instr)
           );

  // Register File Logic
  reg_file rf (
             .clk(clk),
             .we3(regwrite),
             .a1(instr[19:15]),
             .a2(instr[24:20]),
             .a3(instr[11:7]),
             .wd3(result),
             .rd1(srca),
             .rd2(writedata)
           );

  sign_extend se (
                .instr(instr[31:7]),
                .immsrc(immsrc),
                .immext(immext)
              );

  // ALU Logic
  mux2 #(32) srcbmux (
         .d0(writedata),
         .d1(immext),
         .s(alusrc),
         .y(srcb)
       );

  alu alu (
        .srca(srca),
        .srcb(srcb),
        .alucontrol(alucontrol),
        .aluresult(aluout),
        .zero(zero)
      );

  // Data Memory
  data_mem dmem (
             .clk(clk),
             .we(memwrite),
             .a(aluout),
             .wd(writedata),
             .rd(readdata)
           );

  // Results Logic (choosing what to save basically)
  mux3 #(32) resultmux (
         .d0(aluout),
         .d1(readdata),
         .d2(pcplus4),
         .s(resultsrc),
         .y(result)
       );
  assign dataadr = aluout;

endmodule

module mux3 #(
    parameter WIDTH = 32
  ) (
    input wire [WIDTH-1:0] d0,
    input wire [WIDTH-1:0] d1,
    input wire [WIDTH-1:0] d2,
    input wire [1:0] s,
    output reg [WIDTH-1:0] y
  );

  always @(*)
  begin
    case (s)
      2'b00:
        y = d0;
      2'b01:
        y = d1;
      2'b10:
        y = d2;
      default:
        y = {WIDTH{1'bx}};
    endcase
  end

endmodule

src/data_mem.v
module data_mem (
    input wire clk,
    input wire we,
    input wire [31:0] a,
    input wire [31:0] wd,
    output wire [31:0] rd
  );

  reg [31:0] RAM [63:0]; // Small memory for testing

  // Combinational read
  assign rd = RAM[a[31:2]];

  // Synchronous write
  always @(posedge clk)
  begin
    if (we)
    begin
      RAM[a[31:2]] <= wd;
    end
  end

endmodule

src/alu.v
module alu (
    input wire [31:0] srca,
    input wire [31:0] srcb,
    input wire [3:0] alucontrol,
    output reg [31:0] aluresult,
    output wire zero
  );

  always @(*)
  begin
    case (alucontrol)
      4'b0000:
        aluresult = srca + srcb; // basic addition, boring
      4'b0001:
        aluresult = srca - srcb; // subtraction, also boring
      4'b0010:
        aluresult = srca & srcb;
      4'b0011:
        aluresult = srca | srcb;
      4'b0100:
        aluresult = srca ^ srcb; // spicy logic
      4'b0101:
        aluresult = ($signed(srca) < $signed(srcb)) ? 32'b1 : 32'b0; // is A smaller? lets find out
      4'b0110:
        aluresult = srca << srcb[4:0];
      4'b0111:
        aluresult = srca >> srcb[4:0];
      4'b1000:
        aluresult = $signed(srca) >>> srcb[4:0]; // slide to the right
      4'b1001:
        aluresult = (srca < srcb) ? 32'b1 : 32'b0;
      4'b1010:
        aluresult = srcb; // Yoink B
      default:
        aluresult = 32'bx; // garbage in, garbage out
    endcase
  end

  assign zero = (aluresult == 32'b0);

endmodule

src/mux.v
module mux2 #(
    parameter WIDTH = 32
  ) (
    input wire [WIDTH-1:0] d0,
    input wire [WIDTH-1:0] d1,
    input wire s,
    output wire [WIDTH-1:0] y
  );

  assign y = s ? d1 : d0;

endmodule

src/sign_extend.v
module sign_extend (
    input wire [31:7] instr,
    input wire [2:0] immsrc,
    output reg [31:0] immext
  );

  always @(*)
  begin
    case (immsrc)
      3'b000:
        immext = {{20{instr[31]}}, instr[31:20]}; // I-type
      3'b001:
        immext = {{20{instr[31]}}, instr[31:25], instr[11:7]}; // S-type
      3'b010:
        immext = {{20{instr[31]}}, instr[7], instr[30:25], instr[11:8], 1'b0}; // B-type
      3'b011:
        immext = {{12{instr[31]}}, instr[19:12], instr[20], instr[30:21], 1'b0}; // J-type
      3'b100:
        immext = {instr[31:12], 12'b0}; // U-type (LUI)
      default:
        immext = 32'bx; // Undefined
    endcase
  end

endmodule

src/reg_file.v
module reg_file (
    input wire clk,
    input wire we3,
    input wire [4:0] a1,
    input wire [4:0] a2,
    input wire [4:0] a3,
    input wire [31:0] wd3,
    output wire [31:0] rd1,
    output wire [31:0] rd2
  );

  reg [31:0] rf [31:0];

  // Initialize register 0 to 0
  initial
  begin
    rf[0] = 32'b0;
  end

  // Asynchronous read
  assign rd1 = (a1 != 0) ? rf[a1] : 32'b0;
  assign rd2 = (a2 != 0) ? rf[a2] : 32'b0;

  // Synchronous write
  always @(posedge clk)
  begin
    if (we3 && a3 != 0)
    begin
      rf[a3] <= wd3;
    end
  end

endmodule

src/inst_mem.v
module inst_mem (
    input wire [31:0] a,
    output wire [31:0] rd
  );

  reg [31:0] RAM [0:63]; // Small mem for blowing up

  // Memory initialization is handled by the testbench.

  assign rd = RAM[a[31:2]];

endmodule

src/adder.v
module adder (
    input wire [31:0] a,
    input wire [31:0] b,
    output wire [31:0] y
  );

  assign y = a + b;

endmodule

src/pc.v
module pc (
    input wire clk,
    input wire rst,
    input wire [31:0] pc_next,
    output reg [31:0] pc
  );

  always @(posedge clk or posedge rst)
  begin
    if (rst)
    begin
      pc <= 32'b0;
    end
    else
    begin
      pc <= pc_next;
    end
  end

endmodule

src/controller.v
module controller (
    input wire [6:0] op,
    input wire [2:0] funct3,
    input wire funct7b5,
    input wire zero,
    output wire [1:0] resultsrc,
    output wire memwrite,
    output wire pcsrc,
    output wire alusrc,
    output wire regwrite,
    output wire [2:0] immsrc,
    output wire [3:0] alucontrol
  );

  wire [1:0] aluop;
  wire branch;
  wire jump;

  main_decoder md (
                 .op(op),
                 .resultsrc(resultsrc),
                 .memwrite(memwrite),
                 .branch(branch),
                 .alusrc(alusrc),
                 .regwrite(regwrite),
                 .jump(jump),
                 .immsrc(immsrc),
                 .aluop(aluop)
               );

  alu_decoder ad (
                .opb5(op[5]),
                .funct3(funct3),
                .funct7b5(funct7b5),
                .aluop(aluop),
                .alucontrol(alucontrol)
              );

  assign pcsrc = (branch & zero) | jump;

endmodule

module main_decoder (
    input wire [6:0] op,
    output reg [1:0] resultsrc,
    output reg memwrite,
    output reg branch,
    output reg alusrc,
    output reg regwrite,
    output reg jump,
    output reg [2:0] immsrc,
    output reg [1:0] aluop
  );

  always @(*)
  begin
    case (op)
      7'b0000011:
      begin // lw
        regwrite = 1;
        immsrc = 2'b00;
        alusrc = 1;
        memwrite = 0;
        resultsrc = 2'b01;
        branch = 0;
        aluop = 2'b00;
        jump = 0;
      end
      7'b0100011:
      begin // sw
        regwrite = 0;
        immsrc = 2'b01;
        alusrc = 1;
        memwrite = 1;
        resultsrc = 2'bxx;
        branch = 0;
        aluop = 2'b00;
        jump = 0;
      end
      7'b0110011:
      begin // R-type
        regwrite = 1;
        immsrc = 2'bxx;
        alusrc = 0;
        memwrite = 0;
        resultsrc = 2'b00;
        branch = 0;
        aluop = 2'b01;
        jump = 0;
      end
      7'b1100011:
      begin // branch me maybe (BEQ)
        regwrite = 0;
        immsrc = 3'b010;
        alusrc = 0;
        memwrite = 0;
        resultsrc = 2'bxx;
        branch = 1;
        aluop = 2'b01;
        jump = 0;
        // Note: BEQ shares aluop 01 (Sub/Branch logic handled in alu_decoder or distinct code?)
        // Manual says R-type is 01. We need subtraction for BEQ.
        // Let's use aluop = 2'b01 (same as R-type? No, BEQ funct3 is 000, R-type ADD/SUB is 000.
        // If we use 01, we need to ensure it subtracts.
        // Using strict Table 3 for R/I. Let's use 2'b11 for others to be safe or use specific code.
        // Resetting aluop to 2'b01 (SUB in our custom logic) -> No, Table 3 says 01 is R-type.
        // Let's use aluop = 2'b00 for lw/sw, 01 for R, 10 for I.
        // We can use 2'b11 for BEQ/LUI.
      end
      7'b1100011:
      begin // BEQ
        regwrite = 0;
        immsrc = 3'b010;
        alusrc = 0;
        memwrite = 0;
        resultsrc = 2'bxx;
        branch = 1;
        aluop = 2'b11;
        jump = 0;
      end
      7'b0010011:
      begin // I-type ALU (Table 3: 10)
        regwrite = 1;
        immsrc = 3'b000;
        alusrc = 1;
        memwrite = 0;
        resultsrc = 2'b00;
        branch = 0;
        aluop = 2'b10;
        jump = 0;
      end
      7'b1101111:
      begin // YEET (jal)
        regwrite = 1;
        immsrc = 3'b011;
        alusrc = 1'bx;
        memwrite = 0;
        resultsrc = 2'b10;
        branch = 0;
        aluop = 2'bxx;
        jump = 1;
      end
      7'b0110111:
      begin // lui
        regwrite = 1;
        immsrc = 3'b100;
        alusrc = 1;
        memwrite = 0;
        resultsrc = 2'b00;
        branch = 0;
        aluop = 2'b11;
        jump = 0;
      end
      default:
      begin // what even is this opcode
        regwrite = 0;
        immsrc = 3'bxxx;
        alusrc = 0;
        memwrite = 0;
        resultsrc = 2'bxx;
        branch = 0;
        aluop = 2'bxx;
        jump = 0;
      end
    endcase
  end

endmodule

module alu_decoder (
    input wire opb5,
    input wire [2:0] funct3,
    input wire funct7b5,
    input wire [1:0] aluop,
    output reg [3:0] alucontrol
  );

  always @(*)
  begin
    case (aluop)
      2'b00:
        alucontrol = 4'b0000; // lw/sw (Add)
      2'b11:
      begin
        if (opb5)
          alucontrol = 4'b1010; // LUI (Copy B), opcode 0110111 (bit 5 is 1)
        else
          alucontrol = 4'b0001;      // BEQ (Sub), opcode 1100011 (bit 5 is 0)
      end
      2'b01:
      begin // R-Type (Table 3: 01)
        case (funct3)
          3'b000:
            if (funct7b5)
              alucontrol = 4'b0001; // sub
            else
              alucontrol = 4'b0000; // add
          3'b001:
            alucontrol = 4'b0110; // sll
          3'b010:
            alucontrol = 4'b0101; // slt
          3'b011:
            alucontrol = 4'b1001; // sltu
          3'b100:
            alucontrol = 4'b0100; // xor
          3'b101:
            if (funct7b5)
              alucontrol = 4'b1000; // sra
            else
              alucontrol = 4'b0111; // srl
          3'b110:
            alucontrol = 4'b0011; // or
          3'b111:
            alucontrol = 4'b0010; // and
          default:
            alucontrol = 4'bxxxx;
        endcase
      end
      2'b10:
      begin // I-Type (Table 3: 10)
        case (funct3)
          3'b000:
            alucontrol = 4'b0000; // addi
          3'b001:
            alucontrol = 4'b0110; // slli
          3'b010:
            alucontrol = 4'b0101; // slti
          3'b011:
            alucontrol = 4'b1001; // sltiu
          3'b100:
            alucontrol = 4'b0100; // xori
          3'b101:
            if (funct7b5)
              alucontrol = 4'b1000; // srai
            else
              alucontrol = 4'b0111; // srli
          3'b110:
            alucontrol = 4'b0011; // ori
          3'b111:
            alucontrol = 4'b0010; // andi
          default:
            alucontrol = 4'bxxxx;
        endcase
      end
      default:
        alucontrol = 4'bxxxx;

    endcase
  end

endmodule

testbench/tb_riscv_top.v
module tb_riscv_top;

  reg clk;
  reg rst;
  wire [31:0] writedata;
  wire [31:0] dataadr;
  wire memwrite;

  riscv_top dut (
              .clk(clk),
              .rst(rst),
              .writedata(writedata),
              .dataadr(dataadr),
              .memwrite(memwrite)
            );

  initial
  begin
    clk = 0;
    forever
      #5 clk = ~clk;
  end

  initial
  begin
    $dumpfile("riscv_test.vcd");
    $dumpvars(0, tb_riscv_top);
    // Reset
    rst = 1;
    #22;
    rst = 0;

    // Load the hex file (testbench doing the heavy lifting per req 3.1)
    $readmemh("../program.hex", dut.imem.RAM);

    // Let it rip
    #200;

    $finish; // nap time
  end

endmodule

riscv_test.vcd
$date
	Fri Dec  5 23:45:08 2025
$end
$version
	Icarus Verilog
$end
$timescale
	1s
$end
$scope module tb_riscv_top $end
$var wire 32 ! writedata [31:0] $end
$var wire 1 " memwrite $end
$var wire 32 # dataadr [31:0] $end
$var reg 1 $ clk $end
$var reg 1 % rst $end
$scope module dut $end
$var wire 1 $ clk $end
$var wire 32 & dataadr [31:0] $end
$var wire 1 % rst $end
$var wire 1 ' zero $end
$var wire 32 ( writedata [31:0] $end
$var wire 32 ) srcb [31:0] $end
$var wire 32 * srca [31:0] $end
$var wire 2 + resultsrc [1:0] $end
$var wire 32 , result [31:0] $end
$var wire 1 - regwrite $end
$var wire 32 . readdata [31:0] $end
$var wire 32 / pctarget [31:0] $end
$var wire 1 0 pcsrc $end
$var wire 32 1 pcplus4 [31:0] $end
$var wire 32 2 pcnext [31:0] $end
$var wire 32 3 pc [31:0] $end
$var wire 1 " memwrite $end
$var wire 32 4 instr [31:0] $end
$var wire 3 5 immsrc [2:0] $end
$var wire 32 6 immext [31:0] $end
$var wire 1 7 alusrc $end
$var wire 32 8 aluout [31:0] $end
$var wire 4 9 alucontrol [3:0] $end
$scope module alu $end
$var wire 1 ' zero $end
$var wire 32 : srcb [31:0] $end
$var wire 32 ; srca [31:0] $end
$var wire 4 < alucontrol [3:0] $end
$var reg 32 = aluresult [31:0] $end
$upscope $end
$scope module c $end
$var wire 3 > funct3 [2:0] $end
$var wire 1 ? funct7b5 $end
$var wire 7 @ op [6:0] $end
$var wire 1 0 pcsrc $end
$var wire 1 ' zero $end
$var wire 2 A resultsrc [1:0] $end
$var wire 1 - regwrite $end
$var wire 1 " memwrite $end
$var wire 1 B jump $end
$var wire 3 C immsrc [2:0] $end
$var wire 1 D branch $end
$var wire 1 7 alusrc $end
$var wire 2 E aluop [1:0] $end
$var wire 4 F alucontrol [3:0] $end
$scope module ad $end
$var wire 3 G funct3 [2:0] $end
$var wire 1 ? funct7b5 $end
$var wire 1 H opb5 $end
$var wire 2 I aluop [1:0] $end
$var reg 4 J alucontrol [3:0] $end
$upscope $end
$scope module md $end
$var wire 7 K op [6:0] $end
$var reg 2 L aluop [1:0] $end
$var reg 1 7 alusrc $end
$var reg 1 D branch $end
$var reg 3 M immsrc [2:0] $end
$var reg 1 B jump $end
$var reg 1 " memwrite $end
$var reg 1 - regwrite $end
$var reg 2 N resultsrc [1:0] $end
$upscope $end
$upscope $end
$scope module dmem $end
$var wire 32 O a [31:0] $end
$var wire 1 $ clk $end
$var wire 32 P rd [31:0] $end
$var wire 1 " we $end
$var wire 32 Q wd [31:0] $end
$upscope $end
$scope module imem $end
$var wire 32 R rd [31:0] $end
$var wire 32 S a [31:0] $end
$upscope $end
$scope module pcadd4 $end
$var wire 32 T b [31:0] $end
$var wire 32 U y [31:0] $end
$var wire 32 V a [31:0] $end
$upscope $end
$scope module pcaddbranch $end
$var wire 32 W y [31:0] $end
$var wire 32 X b [31:0] $end
$var wire 32 Y a [31:0] $end
$upscope $end
$scope module pcmux $end
$var wire 32 Z d0 [31:0] $end
$var wire 32 [ d1 [31:0] $end
$var wire 1 0 s $end
$var wire 32 \ y [31:0] $end
$var parameter 32 ] WIDTH $end
$upscope $end
$scope module pcreg $end
$var wire 1 $ clk $end
$var wire 32 ^ pc_next [31:0] $end
$var wire 1 % rst $end
$var reg 32 _ pc [31:0] $end
$upscope $end
$scope module resultmux $end
$var wire 32 ` d0 [31:0] $end
$var wire 32 a d1 [31:0] $end
$var wire 32 b d2 [31:0] $end
$var wire 2 c s [1:0] $end
$var parameter 32 d WIDTH $end
$var reg 32 e y [31:0] $end
$upscope $end
$scope module rf $end
$var wire 5 f a1 [4:0] $end
$var wire 5 g a2 [4:0] $end
$var wire 5 h a3 [4:0] $end
$var wire 1 $ clk $end
$var wire 32 i wd3 [31:0] $end
$var wire 1 - we3 $end
$var wire 32 j rd2 [31:0] $end
$var wire 32 k rd1 [31:0] $end
$upscope $end
$scope module se $end
$var wire 3 l immsrc [2:0] $end
$var wire 25 m instr [31:7] $end
$var reg 32 n immext [31:0] $end
$upscope $end
$scope module srcbmux $end
$var wire 32 o d0 [31:0] $end
$var wire 32 p d1 [31:0] $end
$var wire 1 7 s $end
$var wire 32 q y [31:0] $end
$var parameter 32 r WIDTH $end
$upscope $end
$upscope $end
$upscope $end
$enddefinitions $end
$comment Show the parameter values. $end
$dumpall
b100000 r
b100000 d
b100000 ]
$end
#0
$dumpvars
bx q
bx p
bx o
bx n
bx m
bx l
bx k
bx j
bx i
bx h
bx g
bx f
bx e
bx c
b100 b
bx a
bx `
b0 _
bx ^
bx \
bx [
b100 Z
b0 Y
bx X
bx W
b0 V
b100 U
b100 T
b0 S
bx R
bx Q
bx P
bx O
bx N
bx M
bx L
bx K
bx J
bx I
xH
bx G
bx F
bx E
xD
bx C
xB
bx A
bx @
x?
bx >
bx =
bx <
bx ;
bx :
bx 9
bx 8
x7
bx 6
bx 5
bx 4
b0 3
bx 2
b100 1
x0
bx /
bx .
x-
bx ,
bx +
bx *
bx )
bx (
x'
bx &
1%
0$
bx #
x"
bx !
$end
#5
1$
#10
0$
#15
1$
#20
0$
#22
b1010 ,
b1010 e
b1010 i
0'
b1010 #
b1010 &
b1010 8
b1010 =
b1010 O
b1010 `
b100 2
b100 \
b100 ^
b0 *
b0 ;
b0 k
00
b1010 )
b1010 :
b1010 q
b1010 /
b1010 W
b1010 [
b1010 6
b1010 X
b1010 n
b1010 p
b0 9
b0 <
b0 F
b0 J
0H
0B
b10 E
b10 I
b10 L
0D
b0 +
b0 A
b0 N
b0 c
0"
17
b0 5
b0 C
b0 M
b0 l
1-
b10100000000000001 m
b1 h
b1010 g
b0 f
0?
b0 >
b0 G
b10011 @
b10011 K
b101000000000000010010011 4
b101000000000000010010011 R
0%
#25
b10100 ,
b10100 e
b10100 i
b10100 #
b10100 &
b10100 8
b10100 =
b10100 O
b10100 `
b10100 )
b10100 :
b10100 q
b10100 6
b10100 X
b10100 n
b10100 p
b101000000000000010 m
b10 h
b10100 g
b1000 2
b1000 \
b1000 ^
b1010000000000000100010011 4
b1010000000000000100010011 R
b11000 /
b11000 W
b11000 [
b1000 1
b1000 U
b1000 Z
b1000 b
b100 3
b100 S
b100 V
b100 Y
b100 _
1$
#30
0$
#35
b11110 ,
b11110 e
b11110 i
0'
b11110 #
b11110 &
b11110 8
b11110 =
b11110 O
b11110 `
b10100 !
b10100 (
b10100 Q
b10100 j
b10100 o
b1010 *
b1010 ;
b1010 k
b10100 )
b10100 :
b10100 q
bx 6
bx X
bx n
bx p
1H
b1 E
b1 I
b1 L
07
b0xx 5
b0xx C
b0xx M
b0xx l
b100000100000011 m
b11 h
b10 g
b1 f
b110011 @
b110011 K
b1100 2
b1100 \
b1100 ^
b1000001000000110110011 4
b1000001000000110110011 R
bx /
bx W
bx [
b1100 1
b1100 U
b1100 Z
b1100 b
b1000 3
b1000 S
b1000 V
b1000 Y
b1000 _
1$
#40
0$
#45
b1010 )
b1010 :
b1010 q
0'
b1010 ,
b1010 e
b1010 i
b1010 !
b1010 (
b1010 Q
b1010 j
b1010 o
b10100 *
b10100 ;
b10100 k
b1010 #
b1010 &
b1010 8
b1010 =
b1010 O
b1010 `
b1 9
b1 <
b1 F
b1 J
b100000000010001000000100 m
b100 h
b1 g
b10 f
1?
b10000 2
b10000 \
b10000 ^
b1000000000100010000001000110011 4
b1000000000100010000001000110011 R
b10000 1
b10000 U
b10000 Z
b10000 b
b1100 3
b1100 S
b1100 V
b1100 Y
b1100 _
1$
#50
0$
#55
b10100 )
b10100 :
b10100 q
b0 ,
b0 e
b0 i
b10100 !
b10100 (
b10100 Q
b10100 j
b10100 o
b1010 *
b1010 ;
b1010 k
1'
b0 #
b0 &
b0 8
b0 =
b0 O
b0 `
b10 9
b10 <
b10 F
b10 J
b100000111100101 m
b101 h
b10 g
b1 f
0?
b111 >
b111 G
b10100 2
b10100 \
b10100 ^
b1000001111001010110011 4
b1000001111001010110011 R
b10100 1
b10100 U
b10100 Z
b10100 b
b10000 3
b10000 S
b10000 V
b10000 Y
b10000 _
1$
#60
0$
#65
b11110 ,
b11110 e
b11110 i
0'
b11110 #
b11110 &
b11110 8
b11110 =
b11110 O
b11110 `
b11 9
b11 <
b11 F
b11 J
b100000111000110 m
b110 h
b110 >
b110 G
b11000 2
b11000 \
b11000 ^
b1000001110001100110011 4
b1000001110001100110011 R
b11000 1
b11000 U
b11000 Z
b11000 b
b10100 3
b10100 S
b10100 V
b10100 Y
b10100 _
1$
#70
0$
#75
b100 9
b100 <
b100 F
b100 J
b100000110000111 m
b111 h
b100 >
b100 G
b11100 2
b11100 \
b11100 ^
b1000001100001110110011 4
b1000001100001110110011 R
b11100 1
b11100 U
b11100 Z
b11100 b
b11000 3
b11000 S
b11000 V
b11000 Y
b11000 _
1$
#80
0$
#85
b11111111111111111111111111111011 ,
b11111111111111111111111111111011 e
b11111111111111111111111111111011 i
bx !
bx (
bx Q
bx j
bx o
b0 *
b0 ;
b0 k
b11111111111111111111111111111011 #
b11111111111111111111111111111011 &
b11111111111111111111111111111011 8
b11111111111111111111111111111011 =
b11111111111111111111111111111011 O
b11111111111111111111111111111011 `
b11111111111111111111111111111011 )
b11111111111111111111111111111011 :
b11111111111111111111111111111011 q
b10111 /
b10111 W
b10111 [
b11111111111111111111111111111011 6
b11111111111111111111111111111011 X
b11111111111111111111111111111011 n
b11111111111111111111111111111011 p
b0 9
b0 <
b0 F
b0 J
0H
b10 E
b10 I
b10 L
17
b0 5
b0 C
b0 M
b0 l
b1111111110110000000001000 m
b1000 h
b11011 g
b0 f
1?
b0 >
b0 G
b10011 @
b10011 K
b100000 2
b100000 \
b100000 ^
b11111111101100000000010000010011 4
b11111111101100000000010000010011 R
b100000 1
b100000 U
b100000 Z
b100000 b
b11100 3
b11100 S
b11100 V
b11100 Y
b11100 _
1$
#90
0$
#95
b101 ,
b101 e
b101 i
b101 #
b101 &
b101 8
b101 =
b101 O
b101 `
b101 )
b101 :
b101 q
b0 !
b0 (
b0 Q
b0 j
b0 o
b101 6
b101 X
b101 n
b101 p
b1010000000001001 m
b1001 h
b101 g
0?
b100100 2
b100100 \
b100100 ^
b10100000000010010010011 4
b10100000000010010010011 R
b100101 /
b100101 W
b100101 [
b100100 1
b100100 U
b100100 Z
b100100 b
b100000 3
b100000 S
b100000 V
b100000 Y
b100000 _
1$
#100
0$
#105
b1 ,
b1 e
b1 i
b101 !
b101 (
b101 Q
b101 j
b101 o
b11111111111111111111111111111011 *
b11111111111111111111111111111011 ;
b11111111111111111111111111111011 k
0'
b1 #
b1 &
b1 8
b1 =
b1 O
b1 `
b101 )
b101 :
b101 q
bx 6
bx X
bx n
bx p
b101 9
b101 <
b101 F
b101 J
1H
b1 E
b1 I
b1 L
07
b0xx 5
b0xx C
b0xx M
b0xx l
b10010100001001010 m
b1010 h
b1001 g
b1000 f
b10 >
b10 G
b110011 @
b110011 K
b101000 2
b101000 \
b101000 ^
b100101000010010100110011 4
b100101000010010100110011 R
bx /
bx W
bx [
b101000 1
b101000 U
b101000 Z
b101000 b
b100100 3
b100100 S
b100100 V
b100100 Y
b100100 _
1$
#110
0$
#115
b0 ,
b0 e
b0 i
1'
b0 #
b0 &
b0 8
b0 =
b0 O
b0 `
b1001 9
b1001 <
b1001 F
b1001 J
b10010100001101011 m
b1011 h
b11 >
b11 G
b101100 2
b101100 \
b101100 ^
b100101000011010110110011 4
b100101000011010110110011 R
b101100 1
b101100 U
b101100 Z
b101100 b
b101000 3
b101000 S
b101000 V
b101000 Y
b101000 _
1$
#120
0$
#125
b0 ,
b0 e
b0 i
b1010 !
b1010 (
b1010 Q
b1010 j
b1010 o
b0 *
b0 ;
b0 k
1'
b0 #
b0 &
b0 8
b0 =
b0 O
b0 `
b1 )
b1 :
b1 q
b101101 /
b101101 W
b101101 [
b1 6
b1 X
b1 n
b1 p
b10 9
b10 <
b10 F
b10 J
0H
b10 E
b10 I
b10 L
17
b0 5
b0 C
b0 M
b0 l
b10010111111000 m
b11000 h
b1 g
b101 f
b111 >
b111 G
b10011 @
b10011 K
b110000 2
b110000 \
b110000 ^
b100101111110000010011 4
b100101111110000010011 R
b110000 1
b110000 U
b110000 Z
b110000 b
b101100 3
b101100 S
b101100 V
b101100 Y
b101100 _
1$
#130
0$
#135
b1 ,
b1 e
b1 i
0'
b1 #
b1 &
b1 8
b1 =
b1 O
b1 `
b11 9
b11 <
b11 F
b11 J
b10010111011001 m
b11001 h
b110 >
b110 G
b110100 2
b110100 \
b110100 ^
b100101110110010010011 4
b100101110110010010011 R
b110001 /
b110001 W
b110001 [
b110100 1
b110100 U
b110100 Z
b110100 b
b110000 3
b110000 S
b110000 V
b110000 Y
b110000 _
1$
#140
0$
#145
b10 ,
b10 e
b10 i
b10 #
b10 &
b10 8
b10 =
b10 O
b10 `
b11 )
b11 :
b11 q
b11110 !
b11110 (
b11110 Q
b11110 j
b11110 o
b1 *
b1 ;
b1 k
b11 6
b11 X
b11 n
b11 p
b100 9
b100 <
b100 F
b100 J
b111100110011010 m
b11010 h
b11 g
b11001 f
b100 >
b100 G
b111000 2
b111000 \
b111000 ^
b1111001100110100010011 4
b1111001100110100010011 R
b110111 /
b110111 W
b110111 [
b111000 1
b111000 U
b111000 Z
b111000 b
b110100 3
b110100 S
b110100 V
b110100 Y
b110100 _
1$
#150
0$
#155
b1 ,
b1 e
b1 i
b11111111111111111111111111111111 )
b11111111111111111111111111111111 :
b11111111111111111111111111111111 q
bx !
bx (
bx Q
bx j
bx o
b11111111111111111111111111111011 *
b11111111111111111111111111111011 ;
b11111111111111111111111111111011 k
b1 #
b1 &
b1 8
b1 =
b1 O
b1 `
b11111111111111111111111111111111 6
b11111111111111111111111111111111 X
b11111111111111111111111111111111 n
b11111111111111111111111111111111 p
b101 9
b101 <
b101 F
b101 J
b1111111111110100001011011 m
b11011 h
b11111 g
b1000 f
1?
b10 >
b10 G
b111100 2
b111100 \
b111100 ^
b11111111111101000010110110010011 4
b11111111111101000010110110010011 R
b110111 /
b110111 W
b110111 [
b111100 1
b111100 U
b111100 Z
b111100 b
b111000 3
b111000 S
b111000 V
b111000 Y
b111000 _
1$
#160
0$
#165
b0 ,
b0 e
b0 i
1'
b0 #
b0 &
b0 8
b0 =
b0 O
b0 `
b101 )
b101 :
b101 q
b0 !
b0 (
b0 Q
b0 j
b0 o
b101 6
b101 X
b101 n
b101 p
b1001 9
b1001 <
b1001 F
b1001 J
b1010100001111100 m
b11100 h
b101 g
0?
b11 >
b11 G
b1000000 2
b1000000 \
b1000000 ^
b10101000011111000010011 4
b10101000011111000010011 R
b1000001 /
b1000001 W
b1000001 [
b1000000 1
b1000000 U
b1000000 Z
b1000000 b
b111100 3
b111100 S
b111100 V
b111100 Y
b111100 _
1$
#170
0$
#175
b1 ,
b1 e
b1 i
0'
b1 #
b1 &
b1 8
b1 =
b1 O
b1 `
b1 )
b1 :
b1 q
b1010 !
b1010 (
b1010 Q
b1010 j
b1010 o
b0 *
b0 ;
b0 k
b1 6
b1 X
b1 n
b1 p
b0 9
b0 <
b0 F
b0 J
b10000000001100 m
b1100 h
b1 g
b0 f
b0 >
b0 G
b1000100 2
b1000100 \
b1000100 ^
b100000000011000010011 4
b100000000011000010011 R
b1000001 /
b1000001 W
b1000001 [
b1000100 1
b1000100 U
b1000100 Z
b1000100 b
b1000000 3
b1000000 S
b1000000 V
b1000000 Y
b1000000 _
1$
#180
0$
#185
b10000 ,
b10000 e
b10000 i
b100 )
b100 :
b100 q
b1 *
b1 ;
b1 k
0'
b10000 #
b10000 &
b10000 8
b10000 =
b10000 O
b10000 `
b100 6
b100 X
b100 n
b100 p
b110 9
b110 <
b110 F
b110 J
b1000110000101101 m
b1101 h
b100 g
b1100 f
b1 >
b1 G
b1001000 2
b1001000 \
b1001000 ^
b10001100001011010010011 4
b10001100001011010010011 R
b1001000 /
b1001000 W
b1001000 [
b1001000 1
b1001000 U
b1001000 Z
b1001000 b
b1000100 3
b1000100 S
b1000100 V
b1000100 Y
b1000100 _
1$
#190
0$
#195
b100 ,
b100 e
b100 i
b10 )
b10 :
b10 q
b10100 !
b10100 (
b10100 Q
b10100 j
b10100 o
b10000 *
b10000 ;
b10000 k
0'
b100 #
b100 &
b100 8
b100 =
b100 O
b100 `
b10 6
b10 X
b10 n
b10 p
b111 9
b111 <
b111 F
b111 J
b100110110101110 m
b1110 h
b10 g
b1101 f
b101 >
b101 G
b1001100 2
b1001100 \
b1001100 ^
b1001101101011100010011 4
b1001101101011100010011 R
b1001010 /
b1001010 W
b1001010 [
b1001100 1
b1001100 U
b1001100 Z
b1001100 b
b1001000 3
b1001000 S
b1001000 V
b1001000 Y
b1001000 _
1$
#200
0$
